probador.v
/*Se define un modulo "probador", vemos que hacemos un intercambio de salidas
y entradas con respecto al modulo Parte2. */ 
module probador( 
    output reg	clk,  // Salidas del probador.
    output reg 	x,
    output reg 	y,
    output reg 	r,
    output reg 	[2:0]L,
    
    input 		[2:0]Z,  //Entradas del probador. 
    input 		I
);
	

	initial begin
	$dumpfile("PARTE2.vcd"); //Se define el nombre  VCD al compilar por medio del Make. 
	$dumpvars;
	$display ("\t\t\tclk,\tx,\ty,\tr,\tL,\tI,\tZ");
	$monitor($time,"\t%b\t%b\t%b\t%b\t%b\t%b\t%b", clk, x, y, r, L, I, Z);			

	// Valores iniciales
	x <= 0;
        y <= 0;
        r <= 0;
        L[0]<= 0;
        L[1]<= 0;
        L[2]<= 0;


	//30 ciclos con valores random
	repeat(30) begin
		@(posedge clk);

        x<= $random;
        y<= $random;
        r<= $random;
        L[0]<= $random;
        L[1]<= $random;
        L[2]<= $random;
        
	end
		

	//Valores finales
	@(posedge clk);
        x <= 0;
        y <= 0;
        r <= 0;
        L[0]<= 0;
        L[1]<= 0;
        L[2]<= 0;
               


	$finish;  /*Si no se indica lo contrario la simulacion es indefinida, 
                   esto no suele ser deseable, esta función
                indica el final de la simulacion.*/				
end
	initial	begin
		clk 	<= 0;		
	
	end
	always  begin
	  		#10 clk 		<= ~clk;		// Hace "toggle"
	end


 
		

endmodule

Parte2.v
module  celda_ini(   //Definiendo modulo para celda inicial 
    input L,    // Definición de las entradas del modulo

    output reg X,
    output reg Y,
    output reg R,
    output reg Z);
    
    always @(*) begin
    
    	X = L;
    	Y = 0;
    	R = ~L;
    	Z = 0;
    
    end
endmodule

module  celda_tipi(   //Definiendo modulo para celda típica.
    input L,          // Definiendo entradas de la celda
    input x,        
    input y,
    input r,
    output reg X,    //Definiendo salidas de la celda
    output reg Y,
    output reg R,
    output reg Z);
    
    always @(*) begin
    
    /*Se define la función de interes, 
    por medio operadores de Verilog HDL
    */

    	X = (~x & ~r & L) | (~x & ~y & L);
    	
    	Y = (x & ~y & ~r) | ( ~x & y & r);
    	
    	R = ~L;
    	
    	Z = (~x & y & ~r) | (~x & r & L) & (x & ~y & L);
    end
endmodule

module  celda_final( //Definiendo modulo para celda típica.
    input x,         //Definiendo las entradas de la celda
    input y,        
    input r,
    input L,
    output reg I,     //Definiendo las salidas de la celda 
    output reg Z);
    
    always @(*) begin
    
    /*Se define la función de interes, 
    por medio operadores de Verilog HDL
    */

    	I = (r & ~y) | (y & ~r);
    
    	Z = (x & L) + (r & ~L) + (y & ~r & L);
    	
    end
endmodule

banco_prueba.v
`timescale 	1ns				/ 100ps
`include "Parte2.v"
`include "probador.v"

module banco_prueba; 

	//Entradas de la celda inicial, el clk no es entrada.	
	wire x, y, r, clk;
	
	//Conexiones intermedias
	wire X0, Y0, R0;
	
	wire X1, Y1, R1;
	
	//Cables de la salida de la red
	wire [2:0]L;
	wire [2:0]Z;
	wire I;

	celda_ini ini_inst( .L(L[0]), .X(X0), .Y(Y0), .R(R0), .Z(Z[0]));
	
	celda_tipi tipi_inst( .L(L[1]), .x(X0), .y(Y0), .r(R0), .X(X1), .Y(Y1), .R(R1), .Z(Z[1]));
	
    	celda_final final_inst(.L(L[2]), .x(X1), .y(Y1), .r(R1), .I(I), .Z(Z[2]));
	
	//Entradas y salidas de la red, provienen del probador (fuente y osiloscopio XD)
	probador prob_inst( .clk(clk), .x(x), .y(y), .r(r), .L(L), .Z(Z), .I(I));
	
endmodule

PARTE1.vcd
$date
	Mon Jul 26 15:52:34 2021
$end
$version
	Icarus Verilog
$end
$timescale
	100ps
$end
$scope module banco_prueba $end
$var wire 1 ! y $end
$var wire 1 " x $end
$var wire 1 # r $end
$var wire 1 $ clk $end
$var wire 3 % Z [2:0] $end
$var wire 1 & Y1 $end
$var wire 1 ' Y0 $end
$var wire 1 ( X1 $end
$var wire 1 ) X0 $end
$var wire 1 * R1 $end
$var wire 1 + R0 $end
$var wire 3 , L [2:0] $end
$var wire 1 - I $end
$scope module final_inst $end
$var wire 1 . L $end
$var wire 1 & y $end
$var wire 1 ( x $end
$var wire 1 * r $end
$var reg 1 - I $end
$var reg 1 / Z $end
$upscope $end
$scope module ini_inst $end
$var wire 1 0 L $end
$var reg 1 + R $end
$var reg 1 ) X $end
$var reg 1 ' Y $end
$var reg 1 1 Z $end
$upscope $end
$scope module prob_inst $end
$var wire 1 - I $end
$var wire 3 2 Z [2:0] $end
$var reg 3 3 L [2:0] $end
$var reg 1 $ clk $end
$var reg 1 # r $end
$var reg 1 " x $end
$var reg 1 ! y $end
$upscope $end
$scope module tipi_inst $end
$var wire 1 4 L $end
$var wire 1 + r $end
$var wire 1 ) x $end
$var wire 1 ' y $end
$var reg 1 * R $end
$var reg 1 ( X $end
$var reg 1 & Y $end
$var reg 1 5 Z $end
$upscope $end
$upscope $end
$enddefinitions $end
#0
$dumpvars
05
04
b0 3
b100 2
01
00
1/
0.
1-
b0 ,
1+
1*
0)
0(
0'
0&
b100 %
0$
0#
0"
0!
$end
#100
0*
1&
0+
1)
1.
14
10
b111 ,
b111 3
1#
1!
1$
#200
0$
#300
b0 %
b0 2
0/
0-
1*
04
b101 ,
b101 3
0!
1"
1$
#400
0$
#500
0*
0&
1(
1+
0)
0.
14
00
b10 ,
b10 3
1$
#600
0$
#700
b100 %
b100 2
1/
1*
1&
0(
0+
1)
04
10
b1 ,
b1 3
0#
1!
1$
#800
0$
#900
1-
0*
1.
14
b111 ,
b111 3
0"
1$
#1000
0$
#1100
b0 %
b0 2
0/
1*
0&
1+
0)
04
00
b100 ,
b100 3
0!
1"
1$
#1200
0$
#1300
b100 %
b100 2
1/
0*
1&
0+
1)
14
10
b111 ,
b111 3
1#
1!
0"
1$
#1400
0$
#1500
b0 %
b0 2
0/
0.
b11 ,
b11 3
0!
1$
#1600
0$
#1700
0-
0&
1(
1+
0)
00
b10 ,
b10 3
0#
1$
#1800
0$
#1900
b100 %
b100 2
1/
1-
1*
0(
04
b0 ,
b0 3
1#
1!
1$
#2000
0$
#2100
0*
1&
0+
1)
1.
14
10
b111 ,
b111 3
0!
1$
#2200
0$
#2300
0#
1"
1$
#2400
0$
#2500
b0 %
b0 2
0/
0-
1*
04
b101 ,
b101 3
1#
0"
1$
#2600
0$
#2700
1-
0*
0.
14
b11 ,
b11 3
1"
1$
#2800
0$
#2900
b100 %
b100 2
1/
1*
0&
1+
0)
04
00
b0 ,
b0 3
0#
1!
1$
#3000
0$
#3100
0-
0*
1(
1.
14
b110 ,
b110 3
1$
#3200
0$
#3300
1#
1$
#3400
0$
#3500
1-
1*
0(
0.
04
b0 ,
b0 3
0#
0!
1$
#3600
0$
#3700
0*
1&
0+
1)
1.
14
10
b111 ,
b111 3
1#
0"
1$
#3800
0$
#3900
0-
1*
0.
04
b1 ,
b1 3
1"
1$
#4000
0$
#4100
1-
0*
1.
14
b111 ,
b111 3
0#
1!
1$
#4200
0$
#4300
0-
0&
1(
b0 %
b0 2
0/
1+
0)
0.
00
b10 ,
b10 3
0!
1$
#4400
0$
#4500
b100 %
b100 2
1/
1*
1&
0(
0+
1)
04
10
b1 ,
b1 3
1#
0"
1$
#4600
0$
#4700
b0 %
b0 2
0/
0*
0&
1(
1+
0)
14
00
b10 ,
b10 3
0#
1"
1$
#4800
0$
#4900
1-
1&
0(
b100 %
b100 2
1/
0+
1)
1.
10
b111 ,
b111 3
1!
0"
1$
#5000
0$
#5100
b0 %
b0 2
0/
1*
0&
1+
0)
04
00
b100 ,
b100 3
1"
1$
#5200
0$
#5300
0-
1&
b100 %
b100 2
1/
0+
1)
0.
10
b1 ,
b1 3
1#
0!
0"
1$
#5400
0$
#5500
1-
0&
1+
0)
00
b0 ,
b0 3
1!
1$
#5600
0$
#5700
b0 %
b0 2
0/
1.
b100 ,
b100 3
0#
1"
1$
#5800
0$
#5900
b100 %
b100 2
1/
0.
b0 ,
b0 3
1#
0!
0"
1$
#6000
0$
#6100
0#
1$
